streamlit_advanced_plotly_chart/__init__.py
streamlit_advanced_plotly_chart/frontend/build/asset-manifest.json
streamlit_advanced_plotly_chart/frontend/build/bootstrap.min.css
streamlit_advanced_plotly_chart/frontend/build/index.html
streamlit_advanced_plotly_chart/frontend/build/static/js/2.a837515c.chunk.js
streamlit_advanced_plotly_chart/frontend/build/static/js/2.a837515c.chunk.js.LICENSE.txt
streamlit_advanced_plotly_chart/frontend/build/static/js/2.a837515c.chunk.js.map
streamlit_advanced_plotly_chart/frontend/build/static/js/main.31c8f064.chunk.js
streamlit_advanced_plotly_chart/frontend/build/static/js/main.31c8f064.chunk.js.map
streamlit_advanced_plotly_chart/frontend/build/static/js/main.d46ddca9.chunk.js
streamlit_advanced_plotly_chart/frontend/build/static/js/main.d46ddca9.chunk.js.map
streamlit_advanced_plotly_chart/frontend/build/static/js/runtime-main.c6da4008.js
streamlit_advanced_plotly_chart/frontend/build/static/js/runtime-main.c6da4008.js.map
streamlit_advanced_plotly_chart-0.0.2.dist-info/LICENSE
streamlit_advanced_plotly_chart-0.0.2.dist-info/METADATA
streamlit_advanced_plotly_chart-0.0.2.dist-info/WHEEL
streamlit_advanced_plotly_chart-0.0.2.dist-info/top_level.txt
streamlit_advanced_plotly_chart-0.0.2.dist-info/RECORD
