Metadata-Version: 2.1
Name: streamlit-advanced-plotly-chart
Version: 0.0.2
Summary: Custom Streamlit component to preserve zoom level of plotly charts when getting event data from them.
Home-page: https://github.com/fabianandresgrob/streamlit-advanced-plotly-chart
Author: Fabian Grob
Author-email: grobfab@gmail.com
Requires-Python: >=3.6
License-File: LICENSE
Requires-Dist: streamlit (>=0.63)
